MANIFEST.in
base_action_rule_data.xml
base_action_rule_view.xml
setup.py
./__init__.py
./__openerp__.py
./base_action_rule.py
./test_models.py
./tests/__init__.py
./tests/base_action_rule_test.py
i18n/ar.po
i18n/base_action_rule.pot
i18n/bg.po
i18n/bs.po
i18n/ca.po
i18n/cs.po
i18n/da.po
i18n/de.po
i18n/el.po
i18n/es.po
i18n/es_CR.po
i18n/es_EC.po
i18n/es_MX.po
i18n/es_PY.po
i18n/es_VE.po
i18n/fa.po
i18n/fi.po
i18n/fr.po
i18n/gl.po
i18n/gu.po
i18n/he.po
i18n/hr.po
i18n/hu.po
i18n/it.po
i18n/ja.po
i18n/lt.po
i18n/lv.po
i18n/mk.po
i18n/mn.po
i18n/nb.po
i18n/nl.po
i18n/pl.po
i18n/pt.po
i18n/pt_BR.po
i18n/ro.po
i18n/ru.po
i18n/sl.po
i18n/sq.po
i18n/sr.po
i18n/sr@latin.po
i18n/sv.po
i18n/tr.po
i18n/zh_CN.po
i18n/zh_TW.po
images/base_action_rule1.jpeg
images/base_action_rule2.jpeg
images/base_action_rule3.jpeg
openerp_base_action_rule.egg-info/PKG-INFO
openerp_base_action_rule.egg-info/SOURCES.txt
openerp_base_action_rule.egg-info/dependency_links.txt
openerp_base_action_rule.egg-info/requires.txt
openerp_base_action_rule.egg-info/top_level.txt
security/ir.model.access.csv